anghamak/__init__.py
anghamak/content/__init__.py
anghamak/content/vibes_pb2.py
anghamak/content/vibes_pb2_grpc.py
anghamak-0.0.1.dist-info/LICENSE
anghamak-0.0.1.dist-info/METADATA
anghamak-0.0.1.dist-info/WHEEL
anghamak-0.0.1.dist-info/top_level.txt
anghamak-0.0.1.dist-info/RECORD
