Metadata-Version: 2.1
Name: anghamak
Version: 0.0.1
Summary: koussa grpc project
Author-email: Diaa Zaiter <diaa.zaiter@anghami.com>
Classifier: Programming Language :: Python :: 3
Classifier: License :: OSI Approved :: MIT License
Classifier: Operating System :: OS Independent
Requires-Python: >=3.9
License-File: LICENSE
